cp/ConfigParser.py
cp/__init__.py
cp/test.py
cp20240429-0.1.dist-info/METADATA
cp20240429-0.1.dist-info/WHEEL
cp20240429-0.1.dist-info/top_level.txt
cp20240429-0.1.dist-info/RECORD
