Metadata-Version: 2.1
Name: cp20240429
Version: 0.1
Summary: this is test
Home-page: https://blog.csdn.net/landdin2013/article/details/138302331
Author: landdin
Author-email: 394445441@qq.com
